CHANGES.rst
MANIFEST.in
README.rst
example.py
setup.cfg
setup.py
emailsend/__init__.py
emailsend.egg-info/PKG-INFO
emailsend.egg-info/SOURCES.txt
emailsend.egg-info/dependency_links.txt
emailsend.egg-info/not-zip-safe
emailsend.egg-info/top_level.txt