Metadata-Version: 1.1
Name: emailsend
Version: 1.1
Summary: With this module you can easy send emails.
Home-page: http://github.com/filips123/pythonMail
Author: filips
Author-email: filip.stamcar@hotmail.com
License: GNU
Download-URL: https://github.com/filips123/pythonMail/tarball/v1.1
Keywords: mail,python,send email
Platform: any
Classifier: Programming Language :: Python :: 3
